open_geodata/__init__.py
open_geodata/converts/__init__.py
open_geodata/converts/coords.py
open_geodata/converts/coords_lixo.py
open_geodata/converts/files.py
open_geodata/data.py
open_geodata/db/br_amn.json
open_geodata/db/br_cnuc.json
open_geodata/db/br_ibge.json
open_geodata/db/br_icmbio.json
open_geodata/db/br_map_biomas.json
open_geodata/db/sp.json
open_geodata/db/sp_atlas_rural_piracicaba.json
open_geodata/db/sp_bh_at.json
open_geodata/db/sp_bh_pcj_2020_2035.json
open_geodata/db/sp_cati.json
open_geodata/db/sp_defesa_civil.json
open_geodata/db/sp_ff_apa_corumbatai.json
open_geodata/db/sp_mpsp.json
open_geodata/db/sp_piracicaba.json
open_geodata/db/sp_tjsp.json
open_geodata/folium_plus/__init__.py
open_geodata/folium_plus/adds.py
open_geodata/folium_plus/png.py
open_geodata/functions.py
open_geodata/lyr/__init__.py
open_geodata/lyr/base.py
open_geodata/lyr/colors.py
open_geodata/providers/__init__.py
open_geodata/providers/br/__init__.py
open_geodata/providers/br/amn/__init__.py
open_geodata/providers/br/amn/amn.py
open_geodata/providers/br/ibge/__init__.py
open_geodata/providers/br/ibge/geoftp.py
open_geodata/providers/br/ibge/ibge_sidra.py
open_geodata/providers/br/receita_federal/rfb.py
open_geodata/providers/br/sfb/__init__.py
open_geodata/providers/br/sfb/sicar.py
open_geodata/providers/sp/__init__.py
open_geodata/providers/sp/cetesb/div_admin.py
open_geodata/providers/sp/tjsp/div_admin.py
open_geodata-25.9.32.data/data/br_amn.json
open_geodata-25.9.32.data/data/br_cnuc.json
open_geodata-25.9.32.data/data/br_ibge.json
open_geodata-25.9.32.data/data/br_icmbio.json
open_geodata-25.9.32.data/data/br_map_biomas.json
open_geodata-25.9.32.data/data/sp.json
open_geodata-25.9.32.data/data/sp_atlas_rural_piracicaba.json
open_geodata-25.9.32.data/data/sp_bh_at.json
open_geodata-25.9.32.data/data/sp_bh_pcj_2020_2035.json
open_geodata-25.9.32.data/data/sp_cati.json
open_geodata-25.9.32.data/data/sp_defesa_civil.json
open_geodata-25.9.32.dist-info/WHEEL
open_geodata-25.9.32.dist-info/METADATA
open_geodata-25.9.32.dist-info/RECORD
