Metadata-Version: 2.4
Name: open-geodata
Version: 25.9.32
Summary: Dados Espaciais do Brasil
Keywords: geodata,geoprocessamento,github,utility
Author: michelmetran
Author-email: michelmetran <michelmetran@gmail.com>
License-Expression: MIT
Requires-Dist: bmi-arcgis-restapi>=2.4.13
Requires-Dist: fiona>=1.10.1
Requires-Dist: folium>=0.19.7
Requires-Dist: geopandas>=1.1.0
Requires-Dist: mapclassify>=2.9.0
Requires-Dist: matplotlib>=3.10.3
Requires-Dist: more-itertools>=10.7.0
Requires-Dist: openpyxl>=3.1.5
Requires-Dist: owslib>=0.34.1
Requires-Dist: pandas>=2.2.2
Requires-Dist: pooch>=1.8.2
Requires-Dist: py7zr>=1.0.0
Requires-Dist: rarfile>=4.2
Requires-Dist: requests-ip-rotator>=1.0.14
Requires-Dist: selenium>=4.33.0
Requires-Dist: sidrapy>=0.1.4
Requires-Dist: cbers4asat[tools]>=0.9.2 ; extra == 'raster'
Requires-Dist: contextily>=1.6.2 ; extra == 'raster'
Requires-Dist: earthengine-api>=1.5.19 ; extra == 'raster'
Requires-Dist: gdal>=3.8.0 ; extra == 'raster'
Requires-Dist: geemap>=0.35.3 ; extra == 'raster'
Requires-Python: >=3.11
Project-URL: Discussions, https://github.com/michelmetran/open-geodata/discussions
Project-URL: Documentation, https://open-geodata.readthedocs.io/pt/latest/
Project-URL: Issues, https://github.com/michelmetran/open-geodata/issues
Project-URL: Repository, https://github.com/michelmetran/open-geodata
Provides-Extra: raster
